whot/__init__.py
whot/agent.py
whot/deck.py
whot/exceptions.py
whot/game.py
whot/player.py
whot/types.py
whot/utils.py
whot-0.0.6.dist-info/licenses/LICENSE
whot-0.0.6.dist-info/METADATA
whot-0.0.6.dist-info/WHEEL
whot-0.0.6.dist-info/top_level.txt
whot-0.0.6.dist-info/RECORD
